README.md
setup.cfg
setup.py
ie_mbdbl2018_D_yahoo_ks_datareader/__init__.py
ie_mbdbl2018_D_yahoo_ks_datareader.egg-info/PKG-INFO
ie_mbdbl2018_D_yahoo_ks_datareader.egg-info/SOURCES.txt
ie_mbdbl2018_D_yahoo_ks_datareader.egg-info/dependency_links.txt
ie_mbdbl2018_D_yahoo_ks_datareader.egg-info/not-zip-safe
ie_mbdbl2018_D_yahoo_ks_datareader.egg-info/top_level.txt